dir2md.py
dir2md-0.3.1.dist-info/WHEEL
dir2md-0.3.1.dist-info/entry_points.txt
dir2md-0.3.1.dist-info/METADATA
dir2md-0.3.1.dist-info/RECORD
