Metadata-Version: 2.1
Name: dir2md
Version: 0.3.1
Summary: 
License: MIT
Author: IsaacBreen
Author-email: mail@isaacbreen.com
Requires-Python: >=3.8,<4.0
Classifier: License :: OSI Approved :: MIT License
Classifier: Programming Language :: Python :: 3
Classifier: Programming Language :: Python :: 3.8
Classifier: Programming Language :: Python :: 3.9
Classifier: Programming Language :: Python :: 3.10
Classifier: Programming Language :: Python :: 3.11
Requires-Dist: fire (>=0.5.0,<0.6.0)
Requires-Dist: funcparserlib (>=1.0.0,<2.0.0)
